RSSReader/Batch.py
RSSReader/ReadNotice.py
RSSReader/ReadRSS.py
RSSReader/__init__.py
RSSReader-1.0.5.dist-info/License
RSSReader-1.0.5.dist-info/METADATA
RSSReader-1.0.5.dist-info/WHEEL
RSSReader-1.0.5.dist-info/top_level.txt
RSSReader-1.0.5.dist-info/RECORD
