Metadata-Version: 2.1
Name: RSSReader
Version: 1.0.5
Summary: a simple Schedule of RSS Reader
Home-page: UNKNOWN
Author: tim
Author-email: tim_xia@icloud.com
License: UNKNOWN
Platform: UNKNOWN
Classifier: Programming Language :: Python :: 3
Classifier: License :: OSI Approved :: MIT License
Classifier: Operating System :: OS Independent
Requires-Python: >=3.7
